{
    "data": [
        {
            "en": "I work at a convenience store",
            "ko": "나는 편의점에서 일해요"
        },
        {
            "en": "I work at a convenience store with my friend.",
            "ko": "나는 친구와 편의점에서 일해요"
        },
        {
            "en": "She sleeps quietly.",
            "ko": "그녀는 조용히 잠자요."
        },
        {
            "en": "She sleeps quietly in the living room.",
            "ko": "그녀는 거실에서 조용히 잠자요."
        },
        {
            "en": "He eats a little.",
            "ko": "그는 조금 먹어요."
        },
        {
            "en": "He eats a little at the restaurant.",
            "ko": "그는 식당에서 조금 먹어요."
        },
        {
            "en": "We run on the playground.",
            "ko": "우리는 운동장에서 달려요."
        },
        {
            "en": "We run on the playground with the children.",
            "ko": "우리는 아이들과 운동장에서 달려요."
        },
        {
            "en": "They walk hard.",
            "ko": "그들은 열심히 걸어요."
        },
        {
            "en": "They walk hard around the lake.",
            "ko": "그들은 열심히 호수 주변을 걸어요."
        },
        {
            "en": "You sing loudly.",
            "ko": "너는 크게 노래불러."
        },
        {
            "en": "You sing loudly with your classmates.",
            "ko": "너는 크게 반친구들과 노래불러."
        },
        {
            "en": "She listens carefully.",
            "ko": "그여자애는 주의깊게 들어요."
        },
        {
            "en": "She listens carefully in the audience.",
            "ko": "그여자애는 객석에서 주의깊게 들어요."
        },
        {
            "en": "He talks politely.",
            "ko": "그는 정중하게 대화해요."
        },
        {
            "en": "He talks politely at the seminar.",
            "ko": "그는 세미나에서 정중하게 대화해요"
        },
        {
            "en": "We laugh happily.",
            "ko": "우리는 즐겁게 웃어요."
        },
        {
            "en": "We laugh happily at the concert hall.",
            "ko": "우리는 공연장에서 즐겁게 웃어요."
        },
        {
            "en": "They cry sadly.",
            "ko": "그들은 슬프게 울어요."
        },
        {
            "en": "They cry sadly all afternoon.",
            "ko": "그들은 오후내내 슬프게 울어요."
        },
        {
            "en": "You play dangerously.",
            "ko": "너는 위험하게 놀잖아."
        },
        {
            "en": "You play dangerously on the side of the road.",
            "ko": "너는 길가에서 위험하게 놀잖아."
        },
        {
            "en": "I read easily.",
            "ko": "난 쉽게 읽어요."
        },
        {
            "en": "I read easily in English class.",
            "ko": "난 영어시간에 쉽게 읽어요."
        },
        {
            "en": "She writes long.",
            "ko": "그녀는 길게 써요."
        },
        {
            "en": "She writes long by herself.",
            "ko": "그녀는 혼자서 길게 써요."
        },
        {
            "en": "The dog swims barely.",
            "ko": "그 개는 가까스로 수영해요."
        },
        {
            "en": "The dog swims barely across the river.",
            "ko": "그 개는 가까스로 강을 가로질러 수영해요."
        },
        {
            "en": "We drive slowly.",
            "ko": "우리는 천천히 운전해요."
        },
        {
            "en": "We drive slowly in winter.",
            "ko": "우리는 겨울에는 천천히 운전해요."
        },
        {
            "en": "They fly high.",
            "ko": "그것들은 높이 날아요."
        },
        {
            "en": "They fly high over the mountains.",
            "ko": "그것들은 산위를 높이 날아요."
        },
        {
            "en": "I feed right.",
            "ko": "난 제대로 먹이를줘요."
        },
        {
            "en": "I feed right every morning.",
            "ko": "난 아침마다 제대로 먹이를줘요."
        },
        {
            "en": "She learns directly.",
            "ko": "그여자애는 직접적으로 배워요."
        },
        {
            "en": "She learns directly from her mother.",
            "ko": "그녀는 엄마에게 직접적으로 배워요."
        },
        {
            "en": "He cooks deliciously.",
            "ko": "그애가 맛있게 요리해요."
        },
        {
            "en": "He cooks deliciously with fruit.",
            "ko": "그애가 과일로 맛있게 요리해요."
        }
    ]
}