{
    "data": [
{"en": "active", "ko": "활동적인,적극적인,활발한"},
{"en": "actually", "ko": "실제로,정말로,사실은"},
{"en": "advice", "ko": "조언,충고"},
{"en": "airplane", "ko": "비행기"},
{"en": "airport", "ko": "공항"},
{"en": "allow", "ko": "허락하다,용납하다"},
{"en": "amazing", "ko": "놀라운"},
{"en": "area", "ko": "지역,구역"},
{"en": "attend", "ko": "참석하다,(-에)다니다"},
{"en": "bat", "ko": "방망이,박쥐"},
{"en": "believe", "ko": "믿다,(무엇이 가능하다고)여기다"},
{"en": "bill", "ko": "고지서,청구서,지폐"},
{"en": "blow", "ko": "불다"},
{"en": "camp", "ko": "야영지,텐트"},
{"en": "case", "ko": "경우,실정,사례"},
{"en": "century", "ko": "100년,세기"},
{"en": "cheer", "ko": "환호,응원의함성,응원하다"},
{"en": "choice", "ko": "선택,고급의"},
{"en": "collect", "ko": "모으다,수집하다"},
{"en": "contest", "ko": "대회,시합,경쟁을벌이다"},
{"en": "culture", "ko": "문화"},
{"en": "custom", "ko": "관습,습관,주문제작"},
{"en": "decide", "ko": "결정하다,판결을내리다"},
{"en": "electricity", "ko": "전기,전력,열광"},
{"en": "enter", "ko": "들어가다,시작하다"},
{"en": "environment", "ko": "환경"},
{"en": "event", "ko": "사건,행사,경기"},
{"en": "exam", "ko": "시험,검사"},
{"en": "exercise", "ko": "운동,운동하다"},
{"en": "experience", "ko": "경험,경험하다"},
{"en": "express", "ko": "나타내다,표현하다,신속한"},
{"en": "fact", "ko": "사실"},
{"en": "fold", "ko": "접다,접힌부분"},
{"en": "force", "ko": "힘,폭력,-를 강요하다"},
{"en": "forest", "ko": "숲,산림"},
{"en": "form", "ko": "종류,방식,형성되다"},
{"en": "gift", "ko": "선물,재능"},
{"en": "grade", "ko": "품질,등급,나누다,성적을주다"},
{"en": "happen", "ko": "발생하다,일어나다"},
{"en": "human", "ko": "인간의,인간적인,인간"},
{"en": "hunt", "ko": "사냥하다,수색하다,사냥"},
{"en": "important", "ko": "중요한,영향력이 큰"},
{"en": "international", "ko": "국제적인"},
{"en": "island", "ko": "섬"},
{"en": "journey", "ko": "여행,여행하다"},
{"en": "key", "ko": "열쇠,비결,(키보드로)입력하다"},
{"en": "kick", "ko": "차다,발길질"},
{"en": "lazy", "ko": "게으른,느긋한,태만한"},
{"en": "leaf", "ko": "잎,(책의)낱장"},
{"en": "leave", "ko": "떠나다,출발하다"},
{"en": "lie", "ko": "누워있다,눕다,놓여있다"},
{"en": "mad", "ko": "미친,터무니없는,매우화가난"},
{"en": "magazine", "ko": "잡지"},
{"en": "meal", "ko": "식사"},
{"en": "member", "ko": "구성원,회원"},
{"en": "message", "ko": "메시지,메시지를 보내다"},
{"en": "mind", "ko": "마음,정신,상관하다"},
{"en": "modern", "ko": "현대의,근대의,현대적인"},
{"en": "nature", "ko": "자연,천성,본성"},
{"en": "order", "ko": "순서,정된,명령하다,주문하다"},
{"en": "part", "ko": "일부,약간"},
{"en": "path", "ko": "길,계획"},
{"en": "perform", "ko": "행하다,공연하다"},
{"en": "power", "ko": "힘,권력,작동시키다"},
{"en": "protect", "ko": "보호하다,지키다"},
{"en": "public", "ko": "일반인의,공공의,대중"},
{"en": "reach", "ko": "-에 이르다,도달하다,거리,범위"},
{"en": "real", "ko": "진짜의,현실적인"},
{"en": "return", "ko": "돌아오다,반납하다,돌아옴,돌려줌"},
{"en": "review", "ko": "검토,논평,되새기다,복습"},
{"en": "safe", "ko": "안전한"},
{"en": "sand", "ko": "모래"},
{"en": "save", "ko": "구하다,저축하다,저장하다"},
{"en": "scene", "ko": "현장,장면"},
{"en": "secret", "ko": "비밀의,남몰래,비밀,비결"},
{"en": "service", "ko": "서비스"},
{"en": "set", "ko": "놓다,세트,위치한,계획된"},
{"en": "shout", "ko": "외치다,소리치다,고함"},
{"en": "sign", "ko": "징후,조짐,서명하다,계약하다"},
{"en": "simple", "ko": "간단한,소박한,단순한"},
{"en": "soccer", "ko": "축구"},
{"en": "sock", "ko": "양말"},
{"en": "solve", "ko": "해결하다,풀다"},
{"en": "space", "ko": "공간"},
{"en": "special", "ko": "특별한"},
{"en": "spot", "ko": "점,얼룩"},
{"en": "stage", "ko": "단계,개최하다"},
{"en": "step", "ko": "걸음,움직이다"},
{"en": "stick", "ko": "찌르다,찔리다,나뭇가지"},
{"en": "strange", "ko": "이상한,낯선"},
{"en": "stupid", "ko": "어리석은,바보"},
{"en": "succeed", "ko": "성공하다"},
{"en": "symbol", "ko": "상징,부호,기호"},
{"en": "terrible", "ko": "끔찍한,심한,기분이안좋은"},
{"en": "traffic", "ko": "교통량,수송"},
{"en": "treat", "ko": "대하다,취급하다,특별한선물,대접,한턱"},
{"en": "unique", "ko": "독특한,고유의"},
{"en": "upset", "ko": "속상하게 만들다,잘못되게 만들다,속상한,마음이 상한"},
{"en": "usually", "ko": "보통,대개"},
{"en": "wild", "ko": "야생의,자연"}
]}